[{"name":"item 1","ingredients":["beef","fava","egg","goat meet","eggplant"]},{"name":"item 2","ingredients":["cheese","eggplant","chocolate","goat meet"]},{"name":"item 3","ingredients":["lettuce","lemon","chicken","olive oil","basil"]},{"name":"item 4","ingredients":["duck","chicken","pasta","bean","beef","almond","olive oil"]},{"name":"item 5","ingredients":["fava","onion","banana","duck","lettuce"]},{"name":"item 6","ingredients":["fig","chocolate","fava","banana","milk","octopus","olive oil","apple","jalapano","chicken"]},{"name":"item 7","ingredients":["lettuce","lemon","egg","fig"]},{"name":"item 8","ingredients":["goat meet","chocolate","fig","eggplant","chicken","fava","garlic","lettuce","lime","apple"]},{"name":"item 9","ingredients":["peanut","basil","duck","beef","eggplant"]},{"name":"item 10","ingredients":["banana","garlic","onion","cheese","basil","milk","octopus","lime","chicken"]}]